setup.py
grep/__init__.py
grep/internals.py
grep.egg-info/PKG-INFO
grep.egg-info/SOURCES.txt
grep.egg-info/dependency_links.txt
grep.egg-info/not-zip-safe
grep.egg-info/top_level.txt
test/test_matches.py
test/test_pattern.py