Metadata-Version: 1.1
Name: grep
Version: 0.3.1
Summary: String lookup has never been prettier.
Home-page: https://github.com/rinslow/grep
Author: Dan Elkis
Author-email: elkissdan@gmail.com
License: MIT
Keywords: string,lookup,grep
Platform: UNKNOWN
Classifier: License :: OSI Approved :: MIT License
Classifier: Operating System :: OS Independent
Classifier: Programming Language :: Python
Classifier: Programming Language :: Python :: 2
Classifier: Programming Language :: Python :: 2.7
Classifier: Programming Language :: Python :: 3
Classifier: Programming Language :: Python :: 3.4
Classifier: Programming Language :: Python :: 3.5
Classifier: Programming Language :: Python :: 3.6
